pyrealsense2/__init__.py
pyrealsense2/_version.py
pyrealsense2_aarch64-2.23.0.data/scripts/align-depth2color.py
pyrealsense2_aarch64-2.23.0.data/scripts/export_ply_example.py
pyrealsense2_aarch64-2.23.0.data/scripts/opencv_viewer_example.py
pyrealsense2_aarch64-2.23.0.data/scripts/python-rs400-advanced-mode-example.py
pyrealsense2_aarch64-2.23.0.data/scripts/python-tutorial-1-depth.py
pyrealsense2_aarch64-2.23.0.dist-info/DESCRIPTION.rst
pyrealsense2_aarch64-2.23.0.dist-info/METADATA
pyrealsense2_aarch64-2.23.0.dist-info/RECORD
pyrealsense2_aarch64-2.23.0.dist-info/WHEEL
pyrealsense2_aarch64-2.23.0.dist-info/metadata.json
pyrealsense2_aarch64-2.23.0.dist-info/top_level.txt
